LICENSE
MANIFEST.in
README.rst
setup.py
django_inviter.egg-info/PKG-INFO
django_inviter.egg-info/SOURCES.txt
django_inviter.egg-info/dependency_links.txt
django_inviter.egg-info/not-zip-safe
django_inviter.egg-info/requires.txt
django_inviter.egg-info/top_level.txt
example/__init__.py
example/manage.py
example/settings.py
example/urls.py
inviter/__init__.py
inviter/forms.py
inviter/models.py
inviter/tests.py
inviter/tokens.py
inviter/urls.py
inviter/utils.py
inviter/views.py
inviter/migrations/0001_initial.py
inviter/migrations/0002_auto__chg_field_optout_hash.py
inviter/migrations/__init__.py
inviter/templates/inviter/done.html
inviter/templates/inviter/opt-out-done.html
inviter/templates/inviter/opt-out.html
inviter/templates/inviter/register.html
inviter/templates/inviter/email/body.txt
inviter/templates/inviter/email/subject.txt