Metadata-Version: 1.0
Name: django-inviter
Version: 0.2.3
Summary: Invite users to your Django apps
Home-page: UNKNOWN
Author: Alen Mujezinovic
Author-email: alen@caffeinehit.com
License: UNKNOWN
Platform: UNKNOWN
Classifier: Environment :: Web Environment
Classifier: Intended Audience :: Developers
Classifier: License :: OSI Approved :: BSD License
Classifier: Operating System :: OS Independent
Classifier: Programming Language :: Python
Classifier: Framework :: Django
